remove_old_files/__init__.py
remove_old_files/main.py
remove_old_files-1.0.2.dist-info/METADATA
remove_old_files-1.0.2.dist-info/WHEEL
remove_old_files-1.0.2.dist-info/entry_points.txt
remove_old_files-1.0.2.dist-info/top_level.txt
remove_old_files-1.0.2.dist-info/RECORD
