Metadata-Version: 2.1
Name: remove-old-files
Version: 1.0.2
Summary: Simple utility to clear old files from specified folder
Home-page: https://gitlab.com/alda78/remove-old-files
Author: Ales Adamek
Author-email: alda78@seznam.cz
License: MIT
Classifier: Programming Language :: Python :: 3
Classifier: License :: OSI Approved :: MIT License
Classifier: Operating System :: OS Independent
Requires-Python: >=3.5
